{
  "gitSyncId": "66de956ac05adf72589749ca_afd63f43-47b0-471c-8f78-e230c8983736",
  "id": "Manage Company_SP_DELETE_COMPANY",
  "pluginId": "mssql-plugin",
  "pluginType": "DB",
  "unpublishedAction": {
    "actionConfiguration": {
      "body": "EXECUTE  [dbo].[UPDATE_PMS_COMPANY_LM_T]\n   @pCOMPANY_ID = {{COMPANY_ID.text}}\n  ,@pCOMPANY_TYPE = null\n  ,@pCOMPANY_NAME_TH = null\n  ,@pCOMPANY_NAME_EN = null\n  ,@pSHOP_NAME = null\n  ,@pTELEPHONE = null\n\t,@pSTATUS = null\n\t,@pCONTACT_EMAIL = null\n\t,@pCOMPANY_BUSINESS_TYPE = null\n\t,@pFAX = null\n\t,@pTAX_ID = null\n\t,@pWEBSITE = null\n\t,@pCOMPANY_BUILDING_NAME_TH = null\n\t,@pCOMPANY_BUILDING_NAME_EN = null\n\t,@pCOMPANY_FLOOR = null\n\t,@pCOMPANY_ADD_NO = null\n\t,@pCOMPANY_MOO = null\n\t,@pCOMPANY_SOI_TH = null\n\t,@pCOMPANY_SOI_EN = null\n\t,@pCOMPANY_ROAD_TH = null\n\t,@pCOMPANY_ROAD_EN = null\n\t,@pCOMPANY_SUB_DISTRICT = null\n\t,@pCOMPANY_DISTRICT = null\n\t,@pCOMPANY_PROVINCE = null\n\t,@pCOMPANY_POSTAL_CODE = null\n  ,@pUSER_ID = 'test'\n  ,@pDELETE = 1\n\n\n",
      "encodeParamsToggle": true,
      "paginationType": "NONE",
      "pluginSpecifiedTemplates": [
        {
          "value": true
        }
      ],
      "timeoutInMillisecond": 10000
    },
    "confirmBeforeExecute": false,
    "datasource": {
      "id": "UCL_PMS_QAS",
      "isAutoGenerated": false,
      "name": "UCL_PMS_QAS",
      "pluginId": "mssql-plugin"
    },
    "dynamicBindingPathList": [
      {
        "key": "body"
      }
    ],
    "executeOnLoad": false,
    "name": "SP_DELETE_COMPANY",
    "pageId": "Manage Company",
    "userSetOnLoad": false
  }
}